{
    "db_path": "E:\\project_1L\\marketdata\\catalog\\marketdata.duckdb",
    "reports_root": "E:\\project_1L\\marketdata\\backtests",
    "family": "MES",
    "interval": "1m",
    "start_date": "2023-02-26",
    "end_date": "2026-02-22",
    "instrument_mode": "dominant_by_day",
    "instrument_key": null,
    "allow_missing_instrument": false,
    "session_timezone": "America/Chicago",
    "session_start": "08:30",
    "session_end": "15:00",
    "initial_cash": 100000.0,
    "contract_multiplier": 5.0,
    "tick_size": 0.25,
    "slippage_ticks": 1.0,
    "commission_per_side": 1.25,
    "flatten_daily": true,
    "flatten_on_last_bar": true,
    "report_tag": "opening_range_breakout_30m_long_only_1m",
    "strategy": "opening_range_breakout",
    "research_hypothesis": "Testing whether the longer 30-minute opening range improves the long-only ORB variant by reducing false breakout entries.",
    "research_change_description": "ORB refinement from the promoted 15-minute long-only baseline: change range_minutes from 15 to 30 while keeping allow_short=false and all other parameters unchanged.",
    "research_parent_experiment_id": "EXP-20260307-006",
    "research_decision": "TBD",
    "research_recommendation": "TBD",
    "strategy_params": {
        "range_minutes": 30,
        "buffer_ticks": 1,
        "position_size": 1,
        "tick_size": 0.25,
        "session_open": "08:30",
        "no_new_entries_after": "11:00",
        "allow_long": true,
        "allow_short": false,
        "timezone": "America/Chicago"
    },
    "write_daily_equity_csv": true,
    "write_executions_csv": true,
    "write_closed_trades_csv": true
}